{
    "AWSTemplateFormatVersion": "2010-09-09",
    "Description": "This element creates a Public Subnet and associates it with a given Route Table.",
    "Metadata": {
        "Version": "0.0.9"
    },
    "Outputs": {
        "AvailabilityZoneName": {
            "Description": "Name of the Availability Zone where the public subnet was created",
            "Value": {
                "Ref": "AvailabilityZoneName"
            }
        },
        "PublicSubnetCIDR": {
            "Description": "Public Subnet CIDR",
            "Value": {
                "Ref": "CIDRPublicSubnet"
            }
        },
        "PublicSubnetId": {
            "Description": "Subnet ID for the public subnet",
            "Value": {
                "Ref": "PublicSubnet"
            }
        }
    },
    "Parameters": {
        "AvailabilityZoneName": {
            "Description": "Availability Zone Name",
            "Type": "AWS::EC2::AvailabilityZone::Name"
        },
        "CIDRPublicSubnet": {
            "AllowedPattern": "[a-zA-Z0-9]+\\..+",
            "Default": "10.0.32.0/20",
            "Description": "CIDR Block for a Public DMZ Subnet (Example: 10.0.32.0/20, 10.0.96.0/20, etc...)",
            "Type": "String"
        },
        "PublicRouteTableId": {
            "Description": "ID of the Route Table the public subnet will be associated with.",
            "Type": "String"
        },
        "VPC": {
            "Description": "VPC ID",
            "Type": "AWS::EC2::VPC::Id"
        }
    },
    "Resources": {
        "PublicSubnet": {
            "DeletionPolicy": "Retain",
            "Properties": {
                "AvailabilityZone": {
                    "Ref": "AvailabilityZoneName"
                },
                "CidrBlock": {
                    "Ref": "CIDRPublicSubnet"
                },
                "Tags": [
                    {
                        "Key": "Network",
                        "Value": "Public"
                    },
                    {
                        "Key": "Name",
                        "Value": {
                            "Fn::Join": [
                                "",
                                [
                                    "Public-",
                                    {
                                        "Ref": "AWS::StackName"
                                    },
                                    "-",
                                    {
                                        "Ref": "AvailabilityZoneName"
                                    }
                                ]
                            ]
                        }
                    }
                ],
                "VpcId": {
                    "Ref": "VPC"
                }
            },
            "Type": "AWS::EC2::Subnet"
        },
        "PublicSubnetRouteTableAssociation": {
            "DeletionPolicy": "Retain",
            "Properties": {
                "RouteTableId": {
                    "Ref": "PublicRouteTableId"
                },
                "SubnetId": {
                    "Ref": "PublicSubnet"
                }
            },
            "Type": "AWS::EC2::SubnetRouteTableAssociation"
        }
    }
}
